setup.py
paddlepaddle_gpu_installer/__init__.py
paddlepaddle_gpu_installer.egg-info/PKG-INFO
paddlepaddle_gpu_installer.egg-info/SOURCES.txt
paddlepaddle_gpu_installer.egg-info/dependency_links.txt
paddlepaddle_gpu_installer.egg-info/top_level.txt
paddlepaddle_gpu_installer.egg-info/zip-safe